pyenvsync/__init__.py
pyenvsync/_config.py
pyenvsync/_ouput.py
pyenvsync/_requirements.py
pyenvsync/_variables.py
pyenvsync/_version.py
pyenvsync/main.py
pyenvsync-0.1.0.dist-info/LICENCE
pyenvsync-0.1.0.dist-info/METADATA
pyenvsync-0.1.0.dist-info/WHEEL
pyenvsync-0.1.0.dist-info/entry_points.txt
pyenvsync-0.1.0.dist-info/top_level.txt
pyenvsync-0.1.0.dist-info/RECORD
