Metadata-Version: 2.1
Name: pyenvsync
Version: 0.1.0
Summary: PySyncEnv assists with synchronizing and validating Python workspaces across users and devices, ensuring seamless collaboration and consistent setups.
Home-page: https://github.com/mitchell-gottlieb/pyenvsync
Author: Mitchell Gottlieb
Classifier: Development Status :: 1 - Planning
Classifier: Intended Audience :: Developers
Classifier: License :: OSI Approved :: MIT License
Classifier: Programming Language :: Python
Classifier: Programming Language :: Python :: 3
Classifier: Environment :: Console
License-File: LICENCE
